[
  {
    "Aishe Code": "C-62953",
    "Name": "GOVERNMENT MEDICAL COLLEGE BARAMULLA",
    "District": "Baramulla",
    "Course offered": "Diploma of National Board, Bsc Nursing, B.Sc Medical Lab Technology, B.Sc Operation Theatre Technology, B.Sc Renal Dialysis, B.Sc Radiography, B.Sc Anesthesia Technology",
    "Total Student ENROLLED FY 23 24": 139.3520015270026,
    "Total Student ENROLLED FY 22 23": 409.2101422461428,
    "Passed out FY 23 24": 115.02939086703616,
    "Passed out FY 22 23": null,
    "selected for MS FY 23 24": null,
    "selected for MS FY 22 23": null,
    "No of student placed through Campus FY 23 24": 12.449015345170586,
    "No of student placed through Campus FY 22 23": 2.9815186601106887,
    "Average Placement PackageFY 23 24": 1199999.4797095214,
    "Average Placement Package FY 22 23": "4.5 lakh",
    "Hostel facility Yes / No": "Yes",
    "PG Facilities Near college Yes / No": "No",
    "Distance from Railway station": "3.7 km",
    "No of Seats available General": 90.82773623880216,
    "No of Seats available SC / ST": 44.44821283064488,
    "No of Seats available OBC": 11.893195467169289,
    "No of Seats available Girls": 390.630456291624,
    "No of Seats available EWS": 4.378078488483386,
    "No of Seats available Home State": null,
    "No of Seats available Others ": "22",
    "Facilities offer by College Library Yes / No": "Yes",
    "Facilities offer by College Computer Lab Nos": "NO",
    "Facilities offer by College Science Lab No": "1",
    "Facilities offer by College Sports Facility Yes / No": "yes",
    "Facilities offer by College Medical Facility Yes / No": "yes",
    "Facilities offer by College Canteen Yes / No": "yes",
    "Fees Annual Rs in Lac General": 138160.83956572897,
    "Fees Annual Rs in Lac SC / ST": null,
    "Fees Annual Rs in Lac OBC": null,
    "Fees Annual Rs in Lac Girls": null,
    "Fees Annual Rs in Lac EWS": 36000.82507294188,
    "Fees Annual Rs in Lac Home State": null,
    "Fees Annual Rs in Lac Others": "Management Quota - 275000, All India Quota - 250000",
    "Scholarship Annual Rs in Lac General": 25000.134130777995,
    "Scholarship Annual Rs in Lac SC / ST": null,
    "Scholarship Annual Rs in Lac OBC": null,
    "Scholarship Annual Rs in Lac Girls": null,
    "Scholarship Annual Rs in Lac EWS": null,
    "Scholarship Annual Rs in Lac Home State": null,
    "Scholarship Annual Rs in Lac Others": null,
    "Cultural Events Yes / No": "yes",
    "Sports Events Yes / No": "yes",
    "Technical Events Yes / No": null,
    "Others  Events Yes / No": "no"
  },
  {
    "Aishe Code": "C-22882",
    "Name": "Govt. Degree College, Akhnoor",
    "District": "Jammu",
    "Course offered": "B.Sc in Physics Computer App. Maths, B.Sc in Physics Chemistry Maths, B.A in App Maths, Comp App, Hindi, B.A in Maths, B.A in App Maths, Comp App, Economicss B.A in Education Philosophy Sociology, B.A in Pol. Science History Sociology",
    "Total Student ENROLLED FY 23 24": 97.2296297791018,
    "Total Student ENROLLED FY 22 23": 217.3750741164429,
    "Passed out FY 23 24": 114.93555364812303,
    "Passed out FY 22 23": null,
    "selected for MS FY 23 24": null,
    "selected for MS FY 22 23": null,
    "No of student placed through Campus FY 23 24": 14.120360904717216,
    "No of student placed through Campus FY 22 23": 4.580202755610154,
    "Average Placement PackageFY 23 24": 1199999.1412940004,
    "Average Placement Package FY 22 23": "4.5 lakh",
    "Hostel facility Yes / No": "no",
    "PG Facilities Near college Yes / No": "no",
    "Distance from Railway station": "10.7",
    "No of Seats available General": 147.28793341845855,
    "No of Seats available SC / ST": 45.09797977225108,
    "No of Seats available OBC": 13.749599236221814,
    "No of Seats available Girls": 389.2480906384239,
    "No of Seats available EWS": 4.853338197528499,
    "No of Seats available Home State": null,
    "No of Seats available Others ": "Management Quota - 15, All India Quota - 9",
    "Facilities offer by College Library Yes / No": "yes",
    "Facilities offer by College Computer Lab Nos": "1",
    "Facilities offer by College Science Lab No": "5",
    "Facilities offer by College Sports Facility Yes / No": "yes",
    "Facilities offer by College Medical Facility Yes / No": "yes",
    "Facilities offer by College Canteen Yes / No": "yes",
    "Fees Annual Rs in Lac General": -140820.23286141118,
    "Fees Annual Rs in Lac SC / ST": null,
    "Fees Annual Rs in Lac OBC": null,
    "Fees Annual Rs in Lac Girls": null,
    "Fees Annual Rs in Lac EWS": 35999.770729979755,
    "Fees Annual Rs in Lac Home State": null,
    "Fees Annual Rs in Lac Others": "Management Quota - 275000, All India Quota - 250000",
    "Scholarship Annual Rs in Lac General": 24998.755524531865,
    "Scholarship Annual Rs in Lac SC / ST": null,
    "Scholarship Annual Rs in Lac OBC": null,
    "Scholarship Annual Rs in Lac Girls": null,
    "Scholarship Annual Rs in Lac EWS": null,
    "Scholarship Annual Rs in Lac Home State": null,
    "Scholarship Annual Rs in Lac Others": null,
    "Cultural Events Yes / No": "no",
    "Sports Events Yes / No": "yes",
    "Technical Events Yes / No": null,
    "Others  Events Yes / No": "no"
  },
  {
    "Aishe Code": "C-63326",
    "Name": "School of Architecture Govt MAM College Jammu",
    "District": "Jammu",
    "Course offered": "B.Architecture",
    "Total Student ENROLLED FY 23 24": 145.9419906215458,
    "Total Student ENROLLED FY 22 23": 253.85141075263093,
    "Passed out FY 23 24": 115.95777023645024,
    "Passed out FY 22 23": null,
    "selected for MS FY 23 24": null,
    "selected for MS FY 22 23": null,
    "No of student placed through Campus FY 23 24": 14.416769565255365,
    "No of student placed through Campus FY 22 23": 4.313832519605044,
    "Average Placement PackageFY 23 24": 1200002.815258748,
    "Average Placement Package FY 22 23": "4.5 lakh",
    "Hostel facility Yes / No": "yes ",
    "PG Facilities Near college Yes / No": "yes",
    "Distance from Railway station": "10.7",
    "No of Seats available General": 219.1285817466476,
    "No of Seats available SC / ST": 44.67885137495215,
    "No of Seats available OBC": 11.379470840877913,
    "No of Seats available Girls": 392.3735151249346,
    "No of Seats available EWS": 3.579871256903622,
    "No of Seats available Home State": null,
    "No of Seats available Others ": "22",
    "Facilities offer by College Library Yes / No": "yes",
    "Facilities offer by College Computer Lab Nos": "1",
    "Facilities offer by College Science Lab No": "YES",
    "Facilities offer by College Sports Facility Yes / No": "yes",
    "Facilities offer by College Medical Facility Yes / No": "yes",
    "Facilities offer by College Canteen Yes / No": "yes",
    "Fees Annual Rs in Lac General": 222162.93453848327,
    "Fees Annual Rs in Lac SC / ST": null,
    "Fees Annual Rs in Lac OBC": null,
    "Fees Annual Rs in Lac Girls": null,
    "Fees Annual Rs in Lac EWS": 35999.9014393743,
    "Fees Annual Rs in Lac Home State": null,
    "Fees Annual Rs in Lac Others": "Management Quota - 275000, All India Quota - 250000",
    "Scholarship Annual Rs in Lac General": 25000.57817021902,
    "Scholarship Annual Rs in Lac SC / ST": null,
    "Scholarship Annual Rs in Lac OBC": null,
    "Scholarship Annual Rs in Lac Girls": null,
    "Scholarship Annual Rs in Lac EWS": null,
    "Scholarship Annual Rs in Lac Home State": null,
    "Scholarship Annual Rs in Lac Others": null,
    "Cultural Events Yes / No": "no",
    "Sports Events Yes / No": "yes",
    "Technical Events Yes / No": null,
    "Others  Events Yes / No": "no"
  },
  {
    "Aishe Code": "C-46526",
    "Name": "INSTITUTE OF ASIAN MEDICAL SCIENCE AND UNANI",
    "District": "Srinagar",
    "Course offered": "Bachelor of Unani Medicine and Surgery, M.D. (Unani) - Moalajat,  M.D. (Unani) -Ilmul-Advia",
    "Total Student ENROLLED FY 23 24": 28.162812250692863,
    "Total Student ENROLLED FY 22 23": 289.86961080896856,
    "Passed out FY 23 24": 116.40663425544454,
    "Passed out FY 22 23": null,
    "selected for MS FY 23 24": null,
    "selected for MS FY 22 23": null,
    "No of student placed through Campus FY 23 24": 14.18815950401641,
    "No of student placed through Campus FY 22 23": 3.663653329917455,
    "Average Placement PackageFY 23 24": 1200000.3185747715,
    "Average Placement Package FY 22 23": "4.5 lakh",
    "Hostel facility Yes / No": "yes",
    "PG Facilities Near college Yes / No": "no",
    "Distance from Railway station": "21 km",
    "No of Seats available General": 427.6284447793629,
    "No of Seats available SC / ST": 43.48612324536494,
    "No of Seats available OBC": 12.228714941850258,
    "No of Seats available Girls": 388.2340967808745,
    "No of Seats available EWS": 4.579067543744884,
    "No of Seats available Home State": null,
    "No of Seats available Others ": "22",
    "Facilities offer by College Library Yes / No": "yes",
    "Facilities offer by College Computer Lab Nos": "YES",
    "Facilities offer by College Science Lab No": "1",
    "Facilities offer by College Sports Facility Yes / No": "yes",
    "Facilities offer by College Medical Facility Yes / No": "yes",
    "Facilities offer by College Canteen Yes / No": "yes",
    "Fees Annual Rs in Lac General": -83043.60438404192,
    "Fees Annual Rs in Lac SC / ST": null,
    "Fees Annual Rs in Lac OBC": null,
    "Fees Annual Rs in Lac Girls": null,
    "Fees Annual Rs in Lac EWS": 35999.16082902603,
    "Fees Annual Rs in Lac Home State": null,
    "Fees Annual Rs in Lac Others": "Management Quota - 275000, All India Quota - 250000",
    "Scholarship Annual Rs in Lac General": 24999.823581698463,
    "Scholarship Annual Rs in Lac SC / ST": null,
    "Scholarship Annual Rs in Lac OBC": null,
    "Scholarship Annual Rs in Lac Girls": null,
    "Scholarship Annual Rs in Lac EWS": null,
    "Scholarship Annual Rs in Lac Home State": null,
    "Scholarship Annual Rs in Lac Others": null,
    "Cultural Events Yes / No": "yes",
    "Sports Events Yes / No": "yes",
    "Technical Events Yes / No": null,
    "Others  Events Yes / No": "yes"
  },
  {
    "Aishe Code": "C-46528",
    "Name": "SSM COLLEGE OF ENGINEERING",
    "District": "Baramulla",
    "Course offered": "B.Tech. in Civil Engineering, B.Tech. in Electronics and Communication Engineering, B.Tech. in Electrical Engineering, B.Tech. in Mechanical Engineering, B.Tech. in Computer Engineering",
    "Total Student ENROLLED FY 23 24": 138.430687333906,
    "Total Student ENROLLED FY 22 23": 213.1885924890245,
    "Passed out FY 23 24": 116.69964147255013,
    "Passed out FY 22 23": null,
    "selected for MS FY 23 24": null,
    "selected for MS FY 22 23": null,
    "No of student placed through Campus FY 23 24": 14.61157485664492,
    "No of student placed through Campus FY 22 23": 3.824506939812944,
    "Average Placement PackageFY 23 24": 1200000.576805902,
    "Average Placement Package FY 22 23": "4.5 lakh",
    "Hostel facility Yes / No": "yes",
    "PG Facilities Near college Yes / No": "yes",
    "Distance from Railway station": "44 km",
    "No of Seats available General": 163.2601650316562,
    "No of Seats available SC / ST": 45.22054447873236,
    "No of Seats available OBC": 13.048455856397377,
    "No of Seats available Girls": 390.5282536751015,
    "No of Seats available EWS": 4.697673282574535,
    "No of Seats available Home State": null,
    "No of Seats available Others ": "22",
    "Facilities offer by College Library Yes / No": "yes",
    "Facilities offer by College Computer Lab Nos": "YES",
    "Facilities offer by College Science Lab No": "4",
    "Facilities offer by College Sports Facility Yes / No": "yes",
    "Facilities offer by College Medical Facility Yes / No": "yes",
    "Facilities offer by College Canteen Yes / No": "yes",
    "Fees Annual Rs in Lac General": 41047.21267386986,
    "Fees Annual Rs in Lac SC / ST": null,
    "Fees Annual Rs in Lac OBC": null,
    "Fees Annual Rs in Lac Girls": null,
    "Fees Annual Rs in Lac EWS": 35999.03288305034,
    "Fees Annual Rs in Lac Home State": null,
    "Fees Annual Rs in Lac Others": "Management Quota - 275000, All India Quota - 250000",
    "Scholarship Annual Rs in Lac General": 24998.889239705462,
    "Scholarship Annual Rs in Lac SC / ST": null,
    "Scholarship Annual Rs in Lac OBC": null,
    "Scholarship Annual Rs in Lac Girls": null,
    "Scholarship Annual Rs in Lac EWS": null,
    "Scholarship Annual Rs in Lac Home State": null,
    "Scholarship Annual Rs in Lac Others": null,
    "Cultural Events Yes / No": "yes",
    "Sports Events Yes / No": "yes",
    "Technical Events Yes / No": null,
    "Others  Events Yes / No": "yes"
  },
  {
    "Aishe Code": "C-50488",
    "Name": "Govt. Degree  College Bemina, Srinagar",
    "District": "Srinagar",
    "Course offered": "B.A,B.SC,B.Com,BBA,IMBA,IMCOM,IHS,IPS",
    "Total Student ENROLLED FY 23 24": 157.8663607103734,
    "Total Student ENROLLED FY 22 23": 230.95790826941732,
    "Passed out FY 23 24": 114.42872841788292,
    "Passed out FY 22 23": null,
    "selected for MS FY 23 24": null,
    "selected for MS FY 22 23": null,
    "No of student placed through Campus FY 23 24": 13.701600827608718,
    "No of student placed through Campus FY 22 23": 5.646825352985453,
    "Average Placement PackageFY 23 24": 1199999.1062365074,
    "Average Placement Package FY 22 23": "4.5 lakh",
    "Hostel facility Yes / No": "YES",
    "PG Facilities Near college Yes / No": "NO",
    "Distance from Railway station": "20.8",
    "No of Seats available General": 166.27354708704055,
    "No of Seats available SC / ST": 44.6587290424613,
    "No of Seats available OBC": 13.46619491378575,
    "No of Seats available Girls": 389.4476271401981,
    "No of Seats available EWS": 6.660215595410207,
    "No of Seats available Home State": null,
    "No of Seats available Others ": "22",
    "Facilities offer by College Library Yes / No": "NO",
    "Facilities offer by College Computer Lab Nos": "NO",
    "Facilities offer by College Science Lab No": "YES",
    "Facilities offer by College Sports Facility Yes / No": "YES",
    "Facilities offer by College Medical Facility Yes / No": "YES",
    "Facilities offer by College Canteen Yes / No": "YES",
    "Fees Annual Rs in Lac General": 26059.586969608357,
    "Fees Annual Rs in Lac SC / ST": null,
    "Fees Annual Rs in Lac OBC": null,
    "Fees Annual Rs in Lac Girls": null,
    "Fees Annual Rs in Lac EWS": 36000.28750466604,
    "Fees Annual Rs in Lac Home State": null,
    "Fees Annual Rs in Lac Others": "Management Quota - 275000, All India Quota - 250000",
    "Scholarship Annual Rs in Lac General": 24999.515381636804,
    "Scholarship Annual Rs in Lac SC / ST": null,
    "Scholarship Annual Rs in Lac OBC": null,
    "Scholarship Annual Rs in Lac Girls": null,
    "Scholarship Annual Rs in Lac EWS": null,
    "Scholarship Annual Rs in Lac Home State": null,
    "Scholarship Annual Rs in Lac Others": null,
    "Cultural Events Yes / No": "yes ",
    "Sports Events Yes / No": "Yes",
    "Technical Events Yes / No": null,
    "Others  Events Yes / No": "nss"
  },
  {
    "Aishe Code": "C-50489",
    "Name": "G A MEMORIAL COLLEGE OF EDUCATION",
    "District": "Pulwama",
    "Course offered": "B.Ed,D.Ed",
    "Total Student ENROLLED FY 23 24": 80.17037686563681,
    "Total Student ENROLLED FY 22 23": 230.66993879329564,
    "Passed out FY 23 24": 113.89145102408432,
    "Passed out FY 22 23": null,
    "selected for MS FY 23 24": null,
    "selected for MS FY 22 23": null,
    "No of student placed through Campus FY 23 24": 15.449259288585372,
    "No of student placed through Campus FY 22 23": 3.5194055277725407,
    "Average Placement PackageFY 23 24": 1200001.3798239084,
    "Average Placement Package FY 22 23": "4.5 lakh",
    "Hostel facility Yes / No": "yes",
    "PG Facilities Near college Yes / No": "yes",
    "Distance from Railway station": "38",
    "No of Seats available General": 128.5784095165952,
    "No of Seats available SC / ST": 45.0796348477004,
    "No of Seats available OBC": 13.898362716791516,
    "No of Seats available Girls": 391.7215600418765,
    "No of Seats available EWS": 7.200044737620332,
    "No of Seats available Home State": null,
    "No of Seats available Others ": "Management Quota - 15, All India Quota - 9",
    "Facilities offer by College Library Yes / No": "NO",
    "Facilities offer by College Computer Lab Nos": "1",
    "Facilities offer by College Science Lab No": "1",
    "Facilities offer by College Sports Facility Yes / No": "Yes",
    "Facilities offer by College Medical Facility Yes / No": "Yes",
    "Facilities offer by College Canteen Yes / No": "yes ",
    "Fees Annual Rs in Lac General": 50817.35975770987,
    "Fees Annual Rs in Lac SC / ST": null,
    "Fees Annual Rs in Lac OBC": null,
    "Fees Annual Rs in Lac Girls": null,
    "Fees Annual Rs in Lac EWS": 35998.76160330942,
    "Fees Annual Rs in Lac Home State": null,
    "Fees Annual Rs in Lac Others": "Management Quota - 275000, All India Quota - 250000",
    "Scholarship Annual Rs in Lac General": 25000.02404195509,
    "Scholarship Annual Rs in Lac SC / ST": null,
    "Scholarship Annual Rs in Lac OBC": null,
    "Scholarship Annual Rs in Lac Girls": null,
    "Scholarship Annual Rs in Lac EWS": null,
    "Scholarship Annual Rs in Lac Home State": null,
    "Scholarship Annual Rs in Lac Others": null,
    "Cultural Events Yes / No": "yes ",
    "Sports Events Yes / No": "Yes",
    "Technical Events Yes / No": null,
    "Others  Events Yes / No": "no"
  },
  {
    "Aishe Code": "C-50490",
    "Name": "ISLAMIC DISCOVERY OF EDUCATION",
    "District": "Kulgam",
    "Course offered": "B.Ed",
    "Total Student ENROLLED FY 23 24": 112.64645379338585,
    "Total Student ENROLLED FY 22 23": 108.9414019386088,
    "Passed out FY 23 24": 115.70768806928916,
    "Passed out FY 22 23": null,
    "selected for MS FY 23 24": null,
    "selected for MS FY 22 23": null,
    "No of student placed through Campus FY 23 24": 16.911695272585376,
    "No of student placed through Campus FY 22 23": 3.8317392637169663,
    "Average Placement PackageFY 23 24": 1199998.6087929544,
    "Average Placement Package FY 22 23": "4.5 lakh",
    "Hostel facility Yes / No": "YES",
    "PG Facilities Near college Yes / No": "NO",
    "Distance from Railway station": "1.5",
    "No of Seats available General": 231.15580386230997,
    "No of Seats available SC / ST": 46.22110058213355,
    "No of Seats available OBC": 13.320206913423624,
    "No of Seats available Girls": 390.2277692653259,
    "No of Seats available EWS": 6.066529785939175,
    "No of Seats available Home State": null,
    "No of Seats available Others ": "Management Quota - 15, All India Quota - 9",
    "Facilities offer by College Library Yes / No": "YES",
    "Facilities offer by College Computer Lab Nos": "NO",
    "Facilities offer by College Science Lab No": "YES",
    "Facilities offer by College Sports Facility Yes / No": "YES",
    "Facilities offer by College Medical Facility Yes / No": "YES",
    "Facilities offer by College Canteen Yes / No": "YES",
    "Fees Annual Rs in Lac General": 175620.5933943804,
    "Fees Annual Rs in Lac SC / ST": null,
    "Fees Annual Rs in Lac OBC": null,
    "Fees Annual Rs in Lac Girls": null,
    "Fees Annual Rs in Lac EWS": 35999.57663578438,
    "Fees Annual Rs in Lac Home State": null,
    "Fees Annual Rs in Lac Others": "Management Quota - 275000, All India Quota - 250000",
    "Scholarship Annual Rs in Lac General": 25001.772451264387,
    "Scholarship Annual Rs in Lac SC / ST": null,
    "Scholarship Annual Rs in Lac OBC": null,
    "Scholarship Annual Rs in Lac Girls": null,
    "Scholarship Annual Rs in Lac EWS": null,
    "Scholarship Annual Rs in Lac Home State": null,
    "Scholarship Annual Rs in Lac Others": null,
    "Cultural Events Yes / No": "no",
    "Sports Events Yes / No": "yes",
    "Technical Events Yes / No": null,
    "Others  Events Yes / No": "yes"
  },
  {
    "Aishe Code": "C-50491",
    "Name": "PARAMOUNT COLLEGE OF EDUCATION",
    "District": "Pulwama",
    "Course offered": "B.Ed,D.Ed",
    "Total Student ENROLLED FY 23 24": 177.47225802563867,
    "Total Student ENROLLED FY 22 23": 470.1684910801562,
    "Passed out FY 23 24": 115.72003331661382,
    "Passed out FY 22 23": null,
    "selected for MS FY 23 24": null,
    "selected for MS FY 22 23": null,
    "No of student placed through Campus FY 23 24": 12.714007328743364,
    "No of student placed through Campus FY 22 23": 4.267267108611482,
    "Average Placement PackageFY 23 24": 1200001.4333909212,
    "Average Placement Package FY 22 23": "4.5 lakh",
    "Hostel facility Yes / No": "YES",
    "PG Facilities Near college Yes / No": "YES",
    "Distance from Railway station": "2",
    "No of Seats available General": 123.62849881205976,
    "No of Seats available SC / ST": 45.85274805545516,
    "No of Seats available OBC": 12.342151796042906,
    "No of Seats available Girls": 390.33088359736985,
    "No of Seats available EWS": 5.056891378408071,
    "No of Seats available Home State": null,
    "No of Seats available Others ": "22",
    "Facilities offer by College Library Yes / No": "YES",
    "Facilities offer by College Computer Lab Nos": "NO",
    "Facilities offer by College Science Lab No": "YES",
    "Facilities offer by College Sports Facility Yes / No": "YES",
    "Facilities offer by College Medical Facility Yes / No": "YES",
    "Facilities offer by College Canteen Yes / No": "YES",
    "Fees Annual Rs in Lac General": 64102.95225493184,
    "Fees Annual Rs in Lac SC / ST": null,
    "Fees Annual Rs in Lac OBC": null,
    "Fees Annual Rs in Lac Girls": null,
    "Fees Annual Rs in Lac EWS": 35999.66938610328,
    "Fees Annual Rs in Lac Home State": null,
    "Fees Annual Rs in Lac Others": "Management Quota - 275000, All India Quota - 250000",
    "Scholarship Annual Rs in Lac General": 24998.842579354303,
    "Scholarship Annual Rs in Lac SC / ST": null,
    "Scholarship Annual Rs in Lac OBC": null,
    "Scholarship Annual Rs in Lac Girls": null,
    "Scholarship Annual Rs in Lac EWS": null,
    "Scholarship Annual Rs in Lac Home State": null,
    "Scholarship Annual Rs in Lac Others": null,
    "Cultural Events Yes / No": "yes ",
    "Sports Events Yes / No": "yes ",
    "Technical Events Yes / No": null,
    "Others  Events Yes / No": "nss"
  },
  {
    "Aishe Code": "C-50492",
    "Name": "PIONEER COLLEGE OF EDUCATION",
    "District": "Baramulla",
    "Course offered": "B.Ed",
    "Total Student ENROLLED FY 23 24": 211.3756143328104,
    "Total Student ENROLLED FY 22 23": 107.43976978487252,
    "Passed out FY 23 24": 114.77692793332578,
    "Passed out FY 22 23": null,
    "selected for MS FY 23 24": null,
    "selected for MS FY 22 23": null,
    "No of student placed through Campus FY 23 24": 14.311895434052404,
    "No of student placed through Campus FY 22 23": 2.4548532768740063,
    "Average Placement PackageFY 23 24": 1200001.4019299978,
    "Average Placement Package FY 22 23": "4.5 lakh",
    "Hostel facility Yes / No": "YES",
    "PG Facilities Near college Yes / No": "NO",
    "Distance from Railway station": "44 km",
    "No of Seats available General": -5.491904082872395,
    "No of Seats available SC / ST": 45.04485873273824,
    "No of Seats available OBC": 13.729780499815089,
    "No of Seats available Girls": 390.5377817175125,
    "No of Seats available EWS": 3.4672926069654,
    "No of Seats available Home State": null,
    "No of Seats available Others ": "Management Quota - 15, All India Quota - 9",
    "Facilities offer by College Library Yes / No": "YES",
    "Facilities offer by College Computer Lab Nos": "2",
    "Facilities offer by College Science Lab No": "YES",
    "Facilities offer by College Sports Facility Yes / No": "YES",
    "Facilities offer by College Medical Facility Yes / No": "NO",
    "Facilities offer by College Canteen Yes / No": "YES",
    "Fees Annual Rs in Lac General": 125155.87486992838,
    "Fees Annual Rs in Lac SC / ST": null,
    "Fees Annual Rs in Lac OBC": null,
    "Fees Annual Rs in Lac Girls": null,
    "Fees Annual Rs in Lac EWS": 36000.11221478205,
    "Fees Annual Rs in Lac Home State": null,
    "Fees Annual Rs in Lac Others": "Management Quota - 275000, All India Quota - 250000",
    "Scholarship Annual Rs in Lac General": 25000.014903835254,
    "Scholarship Annual Rs in Lac SC / ST": null,
    "Scholarship Annual Rs in Lac OBC": null,
    "Scholarship Annual Rs in Lac Girls": null,
    "Scholarship Annual Rs in Lac EWS": null,
    "Scholarship Annual Rs in Lac Home State": null,
    "Scholarship Annual Rs in Lac Others": null,
    "Cultural Events Yes / No": "yes ",
    "Sports Events Yes / No": "Yes",
    "Technical Events Yes / No": null,
    "Others  Events Yes / No": "yes"
  },
  {
    "Aishe Code": "C-50912",
    "Name": "Government Degree College, Sumbal, Sonawari, ",
    "District": "Bandipora",
    "Course offered": "B.A,B.SC,B.COM",
    "Total Student ENROLLED FY 23 24": 202.0280065482511,
    "Total Student ENROLLED FY 22 23": 129.30296777300816,
    "Passed out FY 23 24": 115.65326294484616,
    "Passed out FY 22 23": null,
    "selected for MS FY 23 24": null,
    "selected for MS FY 22 23": null,
    "No of student placed through Campus FY 23 24": 14.114888262648218,
    "No of student placed through Campus FY 22 23": 5.178327656806798,
    "Average Placement PackageFY 23 24": 1199997.9107444878,
    "Average Placement Package FY 22 23": "4.5 lakh",
    "Hostel facility Yes / No": "YES",
    "PG Facilities Near college Yes / No": "YES",
    "Distance from Railway station": "19.8",
    "No of Seats available General": 147.7155752822701,
    "No of Seats available SC / ST": 46.451244785696616,
    "No of Seats available OBC": 10.880806885503985,
    "No of Seats available Girls": 390.9724822394722,
    "No of Seats available EWS": 3.093529120878263,
    "No of Seats available Home State": null,
    "No of Seats available Others ": "Management Quota - 15, All India Quota - 9",
    "Facilities offer by College Library Yes / No": "YES",
    "Facilities offer by College Computer Lab Nos": "YES",
    "Facilities offer by College Science Lab No": "YES",
    "Facilities offer by College Sports Facility Yes / No": "YES",
    "Facilities offer by College Medical Facility Yes / No": "NO",
    "Facilities offer by College Canteen Yes / No": "YES",
    "Fees Annual Rs in Lac General": 31238.84405955992,
    "Fees Annual Rs in Lac SC / ST": null,
    "Fees Annual Rs in Lac OBC": null,
    "Fees Annual Rs in Lac Girls": null,
    "Fees Annual Rs in Lac EWS": 36000.257785060894,
    "Fees Annual Rs in Lac Home State": null,
    "Fees Annual Rs in Lac Others": "Management Quota - 275000, All India Quota - 250000",
    "Scholarship Annual Rs in Lac General": 24999.36080326305,
    "Scholarship Annual Rs in Lac SC / ST": null,
    "Scholarship Annual Rs in Lac OBC": null,
    "Scholarship Annual Rs in Lac Girls": null,
    "Scholarship Annual Rs in Lac EWS": null,
    "Scholarship Annual Rs in Lac Home State": null,
    "Scholarship Annual Rs in Lac Others": null,
    "Cultural Events Yes / No": "no",
    "Sports Events Yes / No": "Yes",
    "Technical Events Yes / No": null,
    "Others  Events Yes / No": "yes"
  },
  {
    "Aishe Code": "C-22862",
    "Name": "Govt. Degree College, Thanamandi",
    "District": "Rajouri",
    "Course offered": "B.A ,B.SC",
    "Total Student ENROLLED FY 23 24": 112.7594502366962,
    "Total Student ENROLLED FY 22 23": 200.55832967216,
    "Passed out FY 23 24": 114.27999344888126,
    "Passed out FY 22 23": null,
    "selected for MS FY 23 24": null,
    "selected for MS FY 22 23": null,
    "No of student placed through Campus FY 23 24": 13.3647439686947,
    "No of student placed through Campus FY 22 23": 3.040663714539699,
    "Average Placement PackageFY 23 24": 1200000.1685629291,
    "Average Placement Package FY 22 23": "4.5 lakh",
    "Hostel facility Yes / No": "YES",
    "PG Facilities Near college Yes / No": "YES",
    "Distance from Railway station": "21 km",
    "No of Seats available General": 268.0539718767523,
    "No of Seats available SC / ST": 44.07652883716059,
    "No of Seats available OBC": 12.65214602066411,
    "No of Seats available Girls": 389.5449730112727,
    "No of Seats available EWS": 3.272842197263647,
    "No of Seats available Home State": null,
    "No of Seats available Others ": "22",
    "Facilities offer by College Library Yes / No": "YES",
    "Facilities offer by College Computer Lab Nos": "2",
    "Facilities offer by College Science Lab No": "YES",
    "Facilities offer by College Sports Facility Yes / No": "Yes",
    "Facilities offer by College Medical Facility Yes / No": "yes ",
    "Facilities offer by College Canteen Yes / No": "Yes",
    "Fees Annual Rs in Lac General": 11644.378045598867,
    "Fees Annual Rs in Lac SC / ST": null,
    "Fees Annual Rs in Lac OBC": null,
    "Fees Annual Rs in Lac Girls": null,
    "Fees Annual Rs in Lac EWS": 35998.616917619016,
    "Fees Annual Rs in Lac Home State": null,
    "Fees Annual Rs in Lac Others": "Management Quota - 275000, All India Quota - 250000",
    "Scholarship Annual Rs in Lac General": 24998.942964968464,
    "Scholarship Annual Rs in Lac SC / ST": null,
    "Scholarship Annual Rs in Lac OBC": null,
    "Scholarship Annual Rs in Lac Girls": null,
    "Scholarship Annual Rs in Lac EWS": null,
    "Scholarship Annual Rs in Lac Home State": null,
    "Scholarship Annual Rs in Lac Others": null,
    "Cultural Events Yes / No": "no",
    "Sports Events Yes / No": "yes",
    "Technical Events Yes / No": null,
    "Others  Events Yes / No": "no"
  },
  {
    "Aishe Code": "C-22973",
    "Name": "Galaxy College of Education",
    "District": "Jammu",
    "Course offered": "School Of Agriculture & Veterinary Science, School Of Commerce And Management Studies, School Of Hotel Management, School Of Science, School Of Foreign & Indian Languages, School Of Journalism & Mass Media Communication, School Of Philosophy And Research, School Of Engineering & Technology, School Of Computer Science & IT, School Of Architecture & Planning, School Of Library & Information Science, School Of Arts And Social Studies, School Of Education And Physical Education, School Of Law, School Of Pharmacy, School Of Para-Medical Science, School Of Fire & Safety",
    "Total Student ENROLLED FY 23 24": 169.535057400101,
    "Total Student ENROLLED FY 22 23": 296.8680323616151,
    "Passed out FY 23 24": 114.91882218032828,
    "Passed out FY 22 23": null,
    "selected for MS FY 23 24": null,
    "selected for MS FY 22 23": null,
    "No of student placed through Campus FY 23 24": 15.223184601857696,
    "No of student placed through Campus FY 22 23": 4.707130435116087,
    "Average Placement PackageFY 23 24": 1200001.712122955,
    "Average Placement Package FY 22 23": "4.5 lakh",
    "Hostel facility Yes / No": "yes ",
    "PG Facilities Near college Yes / No": "yes",
    "Distance from Railway station": "19.8",
    "No of Seats available General": 363.2337021198116,
    "No of Seats available SC / ST": 45.85948782854489,
    "No of Seats available OBC": 13.244734958579608,
    "No of Seats available Girls": 391.8521696329778,
    "No of Seats available EWS": 4.581085965668593,
    "No of Seats available Home State": null,
    "No of Seats available Others ": "Management Quota - 15, All India Quota - 9",
    "Facilities offer by College Library Yes / No": "yes ",
    "Facilities offer by College Computer Lab Nos": "1",
    "Facilities offer by College Science Lab No": "1",
    "Facilities offer by College Sports Facility Yes / No": "yes",
    "Facilities offer by College Medical Facility Yes / No": "yes",
    "Facilities offer by College Canteen Yes / No": "yes ",
    "Fees Annual Rs in Lac General": 916.9810249844012,
    "Fees Annual Rs in Lac SC / ST": null,
    "Fees Annual Rs in Lac OBC": null,
    "Fees Annual Rs in Lac Girls": null,
    "Fees Annual Rs in Lac EWS": 36001.33454577022,
    "Fees Annual Rs in Lac Home State": null,
    "Fees Annual Rs in Lac Others": "Management Quota - 275000, All India Quota - 250000",
    "Scholarship Annual Rs in Lac General": 24999.74323159193,
    "Scholarship Annual Rs in Lac SC / ST": null,
    "Scholarship Annual Rs in Lac OBC": null,
    "Scholarship Annual Rs in Lac Girls": null,
    "Scholarship Annual Rs in Lac EWS": null,
    "Scholarship Annual Rs in Lac Home State": null,
    "Scholarship Annual Rs in Lac Others": null,
    "Cultural Events Yes / No": "yes ",
    "Sports Events Yes / No": "yes ",
    "Technical Events Yes / No": null,
    "Others  Events Yes / No": "no"
  },
  {
    "Aishe Code": "C-22970",
    "Name": "Govt. Degree College, Udhampur (Boys)",
    "District": "Udhampur",
    "Course offered": "Bachelor of Science, Bachelor of Commerce\r\n, Bachelor of Computer Applications, Bachelor of Arts",
    "Total Student ENROLLED FY 23 24": 95.33542840438824,
    "Total Student ENROLLED FY 22 23": 7.138654981137989,
    "Passed out FY 23 24": 114.55191718845788,
    "Passed out FY 22 23": null,
    "selected for MS FY 23 24": null,
    "selected for MS FY 22 23": null,
    "No of student placed through Campus FY 23 24": 13.931826397938764,
    "No of student placed through Campus FY 22 23": 4.51354213213057,
    "Average Placement PackageFY 23 24": 1199999.7006866809,
    "Average Placement Package FY 22 23": "4.5 lakh",
    "Hostel facility Yes / No": "yes",
    "PG Facilities Near college Yes / No": "yes",
    "Distance from Railway station": "20.8",
    "No of Seats available General": 91.2185538259558,
    "No of Seats available SC / ST": 44.4773509543521,
    "No of Seats available OBC": 12.261216747603973,
    "No of Seats available Girls": 390.2003788476361,
    "No of Seats available EWS": 2.898872984034682,
    "No of Seats available Home State": null,
    "No of Seats available Others ": "Management Quota - 15, All India Quota - 9",
    "Facilities offer by College Library Yes / No": "yes ",
    "Facilities offer by College Computer Lab Nos": "1",
    "Facilities offer by College Science Lab No": "14",
    "Facilities offer by College Sports Facility Yes / No": "YES",
    "Facilities offer by College Medical Facility Yes / No": "yes",
    "Facilities offer by College Canteen Yes / No": "yes",
    "Fees Annual Rs in Lac General": -53179.07002435261,
    "Fees Annual Rs in Lac SC / ST": null,
    "Fees Annual Rs in Lac OBC": null,
    "Fees Annual Rs in Lac Girls": null,
    "Fees Annual Rs in Lac EWS": 36000.00019743313,
    "Fees Annual Rs in Lac Home State": null,
    "Fees Annual Rs in Lac Others": "Management Quota - 275000, All India Quota - 250000",
    "Scholarship Annual Rs in Lac General": 24998.97530396897,
    "Scholarship Annual Rs in Lac SC / ST": null,
    "Scholarship Annual Rs in Lac OBC": null,
    "Scholarship Annual Rs in Lac Girls": null,
    "Scholarship Annual Rs in Lac EWS": null,
    "Scholarship Annual Rs in Lac Home State": null,
    "Scholarship Annual Rs in Lac Others": null,
    "Cultural Events Yes / No": "no",
    "Sports Events Yes / No": "Yes ",
    "Technical Events Yes / No": null,
    "Others  Events Yes / No": "Yes"
  },
  {
    "Aishe Code": "C-22980",
    "Name": "MIER College of Education",
    "District": "Jammu",
    "Course offered": "Ph.D. in Education,M.Ed.,M.A. (Education)M. Phil. Programme,B.Ed.,B.Ed. Special Education(Intellectual Disability),Psychology,English,Political Science,History (as a minor)",
    "Total Student ENROLLED FY 23 24": 134.52723816871912,
    "Total Student ENROLLED FY 22 23": 373.88555876936096,
    "Passed out FY 23 24": 116.51101925495928,
    "Passed out FY 22 23": null,
    "selected for MS FY 23 24": null,
    "selected for MS FY 22 23": null,
    "No of student placed through Campus FY 23 24": 13.084058520405575,
    "No of student placed through Campus FY 22 23": 3.9381408783915313,
    "Average Placement PackageFY 23 24": 1200000.0225186422,
    "Average Placement Package FY 22 23": "4.5 lakh",
    "Hostel facility Yes / No": "no",
    "PG Facilities Near college Yes / No": "yes",
    "Distance from Railway station": " 0.5 km",
    "No of Seats available General": 80.75126502861785,
    "No of Seats available SC / ST": 45.14848127595771,
    "No of Seats available OBC": 11.221718409952956,
    "No of Seats available Girls": 390.1550127363425,
    "No of Seats available EWS": 5.48305104437218,
    "No of Seats available Home State": null,
    "No of Seats available Others ": "Management Quota - 15, All India Quota - 9",
    "Facilities offer by College Library Yes / No": "yes ",
    "Facilities offer by College Computer Lab Nos": "NO",
    "Facilities offer by College Science Lab No": "4",
    "Facilities offer by College Sports Facility Yes / No": "yes ",
    "Facilities offer by College Medical Facility Yes / No": "yes ",
    "Facilities offer by College Canteen Yes / No": "yes ",
    "Fees Annual Rs in Lac General": 225822.75201052657,
    "Fees Annual Rs in Lac SC / ST": null,
    "Fees Annual Rs in Lac OBC": null,
    "Fees Annual Rs in Lac Girls": null,
    "Fees Annual Rs in Lac EWS": 36001.05251954395,
    "Fees Annual Rs in Lac Home State": null,
    "Fees Annual Rs in Lac Others": "Management Quota - 275000, All India Quota - 250000",
    "Scholarship Annual Rs in Lac General": 25000.13271320236,
    "Scholarship Annual Rs in Lac SC / ST": null,
    "Scholarship Annual Rs in Lac OBC": null,
    "Scholarship Annual Rs in Lac Girls": null,
    "Scholarship Annual Rs in Lac EWS": null,
    "Scholarship Annual Rs in Lac Home State": null,
    "Scholarship Annual Rs in Lac Others": null,
    "Cultural Events Yes / No": "yes ",
    "Sports Events Yes / No": "yes ",
    "Technical Events Yes / No": null,
    "Others  Events Yes / No": "Yes"
  },
  {
    "Aishe Code": "C-22981",
    "Name": "Dogra College of Education",
    "District": "Jammu",
    "Course offered": "BEd,MEd",
    "Total Student ENROLLED FY 23 24": 169.85762136559754,
    "Total Student ENROLLED FY 22 23": 169.68558621498067,
    "Passed out FY 23 24": 115.57110499199366,
    "Passed out FY 22 23": null,
    "selected for MS FY 23 24": null,
    "selected for MS FY 22 23": null,
    "No of student placed through Campus FY 23 24": 16.069643933430946,
    "No of student placed through Campus FY 22 23": 4.818110901120617,
    "Average Placement PackageFY 23 24": 1200000.6882633728,
    "Average Placement Package FY 22 23": "4.5 lakh",
    "Hostel facility Yes / No": "yes",
    "PG Facilities Near college Yes / No": "yes",
    "Distance from Railway station": "48",
    "No of Seats available General": 166.63893538842223,
    "No of Seats available SC / ST": 45.74567447326606,
    "No of Seats available OBC": 11.846510807882437,
    "No of Seats available Girls": 390.5695963342933,
    "No of Seats available EWS": 3.706431900819791,
    "No of Seats available Home State": null,
    "No of Seats available Others ": "22",
    "Facilities offer by College Library Yes / No": "yes ",
    "Facilities offer by College Computer Lab Nos": "1",
    "Facilities offer by College Science Lab No": "1",
    "Facilities offer by College Sports Facility Yes / No": "yes ",
    "Facilities offer by College Medical Facility Yes / No": "yes ",
    "Facilities offer by College Canteen Yes / No": "yes ",
    "Fees Annual Rs in Lac General": 153096.60503434754,
    "Fees Annual Rs in Lac SC / ST": null,
    "Fees Annual Rs in Lac OBC": null,
    "Fees Annual Rs in Lac Girls": null,
    "Fees Annual Rs in Lac EWS": 36001.77877906009,
    "Fees Annual Rs in Lac Home State": null,
    "Fees Annual Rs in Lac Others": "Management Quota - 275000, All India Quota - 250000",
    "Scholarship Annual Rs in Lac General": 24998.11086093639,
    "Scholarship Annual Rs in Lac SC / ST": null,
    "Scholarship Annual Rs in Lac OBC": null,
    "Scholarship Annual Rs in Lac Girls": null,
    "Scholarship Annual Rs in Lac EWS": null,
    "Scholarship Annual Rs in Lac Home State": null,
    "Scholarship Annual Rs in Lac Others": null,
    "Cultural Events Yes / No": "yes ",
    "Sports Events Yes / No": "yes ",
    "Technical Events Yes / No": null,
    "Others  Events Yes / No": "nss"
  },
  {
    "Aishe Code": "C-30795",
    "Name": "Govt. Degree College for Women, Kathua",
    "District": "Kathua",
    "Course offered": "B.Sc. Zoology, B.Sc. Geography, B.Sc. Computer applications,B.Sc. Botany,B.Sc. Physics,BA (Sociology),BA Political Science,BA Hindi,BA Education,BA Dogri, BA Administration, BA Economics",
    "Total Student ENROLLED FY 23 24": 113.69728518665258,
    "Total Student ENROLLED FY 22 23": 114.57945349967429,
    "Passed out FY 23 24": 115.21046543759806,
    "Passed out FY 22 23": null,
    "selected for MS FY 23 24": null,
    "selected for MS FY 22 23": null,
    "No of student placed through Campus FY 23 24": 12.998304503193737,
    "No of student placed through Campus FY 22 23": 4.052474455133559,
    "Average Placement PackageFY 23 24": 1200000.632422841,
    "Average Placement Package FY 22 23": "4.5 lakh",
    "Hostel facility Yes / No": "No",
    "PG Facilities Near college Yes / No": "no",
    "Distance from Railway station": "8.1",
    "No of Seats available General": 440.7234960591143,
    "No of Seats available SC / ST": 43.609638331994965,
    "No of Seats available OBC": 12.59625156132872,
    "No of Seats available Girls": 389.1363118912796,
    "No of Seats available EWS": 4.399029330983776,
    "No of Seats available Home State": null,
    "No of Seats available Others ": "22",
    "Facilities offer by College Library Yes / No": "Yes",
    "Facilities offer by College Computer Lab Nos": "1",
    "Facilities offer by College Science Lab No": "5",
    "Facilities offer by College Sports Facility Yes / No": "yes",
    "Facilities offer by College Medical Facility Yes / No": "yes ",
    "Facilities offer by College Canteen Yes / No": "Yes",
    "Fees Annual Rs in Lac General": 11200.0,
    "Fees Annual Rs in Lac SC / ST": null,
    "Fees Annual Rs in Lac OBC": null,
    "Fees Annual Rs in Lac Girls": null,
    "Fees Annual Rs in Lac EWS": 35998.89697463857,
    "Fees Annual Rs in Lac Home State": null,
    "Fees Annual Rs in Lac Others": "Management Quota - 275000, All India Quota - 250000",
    "Scholarship Annual Rs in Lac General": 24998.712317930247,
    "Scholarship Annual Rs in Lac SC / ST": null,
    "Scholarship Annual Rs in Lac OBC": null,
    "Scholarship Annual Rs in Lac Girls": null,
    "Scholarship Annual Rs in Lac EWS": null,
    "Scholarship Annual Rs in Lac Home State": null,
    "Scholarship Annual Rs in Lac Others": null,
    "Cultural Events Yes / No": "yes",
    "Sports Events Yes / No": "Yes",
    "Technical Events Yes / No": null,
    "Others  Events Yes / No": "no"
  },
  {
    "Aishe Code": "C-30799",
    "Name": "Ramisht College of Education",
    "District": "Kathua",
    "Course offered": "B.Ed",
    "Total Student ENROLLED FY 23 24": 102.60589486247136,
    "Total Student ENROLLED FY 22 23": 294.4402840614045,
    "Passed out FY 23 24": 114.20434568461316,
    "Passed out FY 22 23": null,
    "selected for MS FY 23 24": null,
    "selected for MS FY 22 23": null,
    "No of student placed through Campus FY 23 24": 15.327223135489042,
    "No of student placed through Campus FY 22 23": 4.956577317013648,
    "Average Placement PackageFY 23 24": 1199999.388372067,
    "Average Placement Package FY 22 23": "4.5 lakh",
    "Hostel facility Yes / No": "Yes",
    "PG Facilities Near college Yes / No": "YES",
    "Distance from Railway station": "38",
    "No of Seats available General": 112.0545336318512,
    "No of Seats available SC / ST": 45.74594426361947,
    "No of Seats available OBC": 14.128080450684124,
    "No of Seats available Girls": 389.7832702964866,
    "No of Seats available EWS": 5.839363123778955,
    "No of Seats available Home State": null,
    "No of Seats available Others ": "22",
    "Facilities offer by College Library Yes / No": "Yes",
    "Facilities offer by College Computer Lab Nos": "2",
    "Facilities offer by College Science Lab No": "14",
    "Facilities offer by College Sports Facility Yes / No": "Yes",
    "Facilities offer by College Medical Facility Yes / No": "Yes",
    "Facilities offer by College Canteen Yes / No": "Yes",
    "Fees Annual Rs in Lac General": -151298.74771029147,
    "Fees Annual Rs in Lac SC / ST": null,
    "Fees Annual Rs in Lac OBC": null,
    "Fees Annual Rs in Lac Girls": null,
    "Fees Annual Rs in Lac EWS": 35999.31117289284,
    "Fees Annual Rs in Lac Home State": null,
    "Fees Annual Rs in Lac Others": "Management Quota - 275000, All India Quota - 250000",
    "Scholarship Annual Rs in Lac General": 24999.40716102027,
    "Scholarship Annual Rs in Lac SC / ST": null,
    "Scholarship Annual Rs in Lac OBC": null,
    "Scholarship Annual Rs in Lac Girls": null,
    "Scholarship Annual Rs in Lac EWS": null,
    "Scholarship Annual Rs in Lac Home State": null,
    "Scholarship Annual Rs in Lac Others": null,
    "Cultural Events Yes / No": "yes ",
    "Sports Events Yes / No": "yes",
    "Technical Events Yes / No": null,
    "Others  Events Yes / No": "yes"
  },
  {
    "Aishe Code": "C-30800",
    "Name": "KC College of Education",
    "District": "Jammu",
    "Course offered": "B.Ed",
    "Total Student ENROLLED FY 23 24": 168.1925459028536,
    "Total Student ENROLLED FY 22 23": 161.02707044677464,
    "Passed out FY 23 24": 117.49040312616944,
    "Passed out FY 22 23": null,
    "selected for MS FY 23 24": null,
    "selected for MS FY 22 23": null,
    "No of student placed through Campus FY 23 24": 15.309740671470257,
    "No of student placed through Campus FY 22 23": 4.971127708446946,
    "Average Placement PackageFY 23 24": 1199999.9103193984,
    "Average Placement Package FY 22 23": "4.5 lakh",
    "Hostel facility Yes / No": "yes",
    "PG Facilities Near college Yes / No": "NO",
    "Distance from Railway station": "155",
    "No of Seats available General": 83.4735618062506,
    "No of Seats available SC / ST": 44.97143181031751,
    "No of Seats available OBC": 13.864465236872396,
    "No of Seats available Girls": 389.0156967060464,
    "No of Seats available EWS": 4.300413149947088,
    "No of Seats available Home State": null,
    "No of Seats available Others ": "Management Quota - 15, All India Quota - 9",
    "Facilities offer by College Library Yes / No": "Yes",
    "Facilities offer by College Computer Lab Nos": "NO",
    "Facilities offer by College Science Lab No": "4",
    "Facilities offer by College Sports Facility Yes / No": "yes ",
    "Facilities offer by College Medical Facility Yes / No": "YES",
    "Facilities offer by College Canteen Yes / No": "yes",
    "Fees Annual Rs in Lac General": 34000.0,
    "Fees Annual Rs in Lac SC / ST": null,
    "Fees Annual Rs in Lac OBC": null,
    "Fees Annual Rs in Lac Girls": null,
    "Fees Annual Rs in Lac EWS": 35998.89458744578,
    "Fees Annual Rs in Lac Home State": null,
    "Fees Annual Rs in Lac Others": "Management Quota - 275000, All India Quota - 250000",
    "Scholarship Annual Rs in Lac General": 24999.943439694685,
    "Scholarship Annual Rs in Lac SC / ST": null,
    "Scholarship Annual Rs in Lac OBC": null,
    "Scholarship Annual Rs in Lac Girls": null,
    "Scholarship Annual Rs in Lac EWS": null,
    "Scholarship Annual Rs in Lac Home State": null,
    "Scholarship Annual Rs in Lac Others": null,
    "Cultural Events Yes / No": "Yes",
    "Sports Events Yes / No": "Yes ",
    "Technical Events Yes / No": null,
    "Others  Events Yes / No": "yes"
  },
  {
    "Aishe Code": "C-51584",
    "Name": "Zakura Campus, University of Kashmir",
    "District": "Srinagar",
    "Course offered": "B. Tech. Mechanical Engineering, B. Tech. Electrical Engineering, B.Tech. E & C Engineering, B. Tech. Civil Engineering, B.Tech. Computer Science Engineering, M.Tech. Design Engineering, M.Tech. Power System and Control, M.Tech. Electronics & Communication Engineering",
    "Total Student ENROLLED FY 23 24": 149.0,
    "Total Student ENROLLED FY 22 23": 147.0,
    "Passed out FY 23 24": 114.40077610567089,
    "Passed out FY 22 23": null,
    "selected for MS FY 23 24": null,
    "selected for MS FY 22 23": null,
    "No of student placed through Campus FY 23 24": 14.0,
    "No of student placed through Campus FY 22 23": 4.0,
    "Average Placement PackageFY 23 24": 1200000.0,
    "Average Placement Package FY 22 23": "4.5 lakh",
    "Hostel facility Yes / No": "yes ",
    "PG Facilities Near college Yes / No": "No",
    "Distance from Railway station": "1.5",
    "No of Seats available General": 410.0,
    "No of Seats available SC / ST": 45.18933191319788,
    "No of Seats available OBC": 14.490277829794248,
    "No of Seats available Girls": 390.46123372278674,
    "No of Seats available EWS": 5.69673407659004,
    "No of Seats available Home State": null,
    "No of Seats available Others ": "22",
    "Facilities offer by College Library Yes / No": "Yes",
    "Facilities offer by College Computer Lab Nos": "1",
    "Facilities offer by College Science Lab No": "14",
    "Facilities offer by College Sports Facility Yes / No": "YES",
    "Facilities offer by College Medical Facility Yes / No": "yes ",
    "Facilities offer by College Canteen Yes / No": "YES",
    "Fees Annual Rs in Lac General": 128067.27339855777,
    "Fees Annual Rs in Lac SC / ST": null,
    "Fees Annual Rs in Lac OBC": null,
    "Fees Annual Rs in Lac Girls": null,
    "Fees Annual Rs in Lac EWS": 36000.77606660179,
    "Fees Annual Rs in Lac Home State": null,
    "Fees Annual Rs in Lac Others": "Management Quota - 275000, All India Quota - 250000",
    "Scholarship Annual Rs in Lac General": 24999.633264374115,
    "Scholarship Annual Rs in Lac SC / ST": null,
    "Scholarship Annual Rs in Lac OBC": null,
    "Scholarship Annual Rs in Lac Girls": null,
    "Scholarship Annual Rs in Lac EWS": null,
    "Scholarship Annual Rs in Lac Home State": null,
    "Scholarship Annual Rs in Lac Others": null,
    "Cultural Events Yes / No": "Yes",
    "Sports Events Yes / No": "Yes",
    "Technical Events Yes / No": null,
    "Others  Events Yes / No": "Yes"
  },
  {
    "Aishe Code": "C-46527",
    "Name": "KASHMIR TIBBIA COLLEGE",
    "District": "Bandipora",
    "Course offered": "Bachelor of Unani Medicine and Surgery (B.U.M.S)",
    "Total Student ENROLLED FY 23 24": 162.8229435839189,
    "Total Student ENROLLED FY 22 23": 281.6432906192211,
    "Passed out FY 23 24": 114.18065724166294,
    "Passed out FY 22 23": null,
    "selected for MS FY 23 24": null,
    "selected for MS FY 22 23": null,
    "No of student placed through Campus FY 23 24": 12.085292306709205,
    "No of student placed through Campus FY 22 23": 1.683299533878265,
    "Average Placement PackageFY 23 24": 1200000.6027065015,
    "Average Placement Package FY 22 23": "4.5 lakh",
    "Hostel facility Yes / No": "Yes",
    "PG Facilities Near college Yes / No": "yes",
    "Distance from Railway station": "18.5",
    "No of Seats available General": 31.0,
    "No of Seats available SC / ST": 44.8184152309146,
    "No of Seats available OBC": 12.748172136828154,
    "No of Seats available Girls": 391.2891723905515,
    "No of Seats available EWS": 5.0,
    "No of Seats available Home State": null,
    "No of Seats available Others ": "Management Quota - 15, All India Quota - 9",
    "Facilities offer by College Library Yes / No": "Yes",
    "Facilities offer by College Computer Lab Nos": "YES",
    "Facilities offer by College Science Lab No": "4",
    "Facilities offer by College Sports Facility Yes / No": "Yes",
    "Facilities offer by College Medical Facility Yes / No": "Yes",
    "Facilities offer by College Canteen Yes / No": "Yes",
    "Fees Annual Rs in Lac General": 175000.0,
    "Fees Annual Rs in Lac SC / ST": null,
    "Fees Annual Rs in Lac OBC": null,
    "Fees Annual Rs in Lac Girls": null,
    "Fees Annual Rs in Lac EWS": 36000.0,
    "Fees Annual Rs in Lac Home State": null,
    "Fees Annual Rs in Lac Others": "Management Quota - 275000, All India Quota - 250000",
    "Scholarship Annual Rs in Lac General": 25000.0,
    "Scholarship Annual Rs in Lac SC / ST": null,
    "Scholarship Annual Rs in Lac OBC": null,
    "Scholarship Annual Rs in Lac Girls": null,
    "Scholarship Annual Rs in Lac EWS": null,
    "Scholarship Annual Rs in Lac Home State": null,
    "Scholarship Annual Rs in Lac Others": null,
    "Cultural Events Yes / No": "Yes",
    "Sports Events Yes / No": "Yes",
    "Technical Events Yes / No": null,
    "Others  Events Yes / No": "Yes"
  },
  {
    "Aishe Code": "C-46538",
    "Name": "VITASTA SCHOOL OF LAW  AND HUMANITIES",
    "District": "Budgam",
    "Course offered": "B.A LL.B",
    "Total Student ENROLLED FY 23 24": 163.8213664248758,
    "Total Student ENROLLED FY 22 23": 167.7986136124324,
    "Passed out FY 23 24": 115.92076014117028,
    "Passed out FY 22 23": null,
    "selected for MS FY 23 24": null,
    "selected for MS FY 22 23": null,
    "No of student placed through Campus FY 23 24": 17.179679931524763,
    "No of student placed through Campus FY 22 23": 6.149148998969967,
    "Average Placement PackageFY 23 24": 1200001.5897192778,
    "Average Placement Package FY 22 23": "4.5 lakh",
    "Hostel facility Yes / No": "YES",
    "PG Facilities Near college Yes / No": "YES",
    "Distance from Railway station": "1.5",
    "No of Seats available General": 120.0,
    "No of Seats available SC / ST": 44.712837016346015,
    "No of Seats available OBC": 13.55964263937774,
    "No of Seats available Girls": 390.00481699667273,
    "No of Seats available EWS": 4.715495543724291,
    "No of Seats available Home State": null,
    "No of Seats available Others ": "Management Quota - 15, All India Quota - 9",
    "Facilities offer by College Library Yes / No": "Yes",
    "Facilities offer by College Computer Lab Nos": "1",
    "Facilities offer by College Science Lab No": "YES",
    "Facilities offer by College Sports Facility Yes / No": "Yes",
    "Facilities offer by College Medical Facility Yes / No": "YES",
    "Facilities offer by College Canteen Yes / No": "yes ",
    "Fees Annual Rs in Lac General": -14771.149464698348,
    "Fees Annual Rs in Lac SC / ST": null,
    "Fees Annual Rs in Lac OBC": null,
    "Fees Annual Rs in Lac Girls": null,
    "Fees Annual Rs in Lac EWS": 36000.29389598096,
    "Fees Annual Rs in Lac Home State": null,
    "Fees Annual Rs in Lac Others": "Management Quota - 275000, All India Quota - 250000",
    "Scholarship Annual Rs in Lac General": 25001.189554722565,
    "Scholarship Annual Rs in Lac SC / ST": null,
    "Scholarship Annual Rs in Lac OBC": null,
    "Scholarship Annual Rs in Lac Girls": null,
    "Scholarship Annual Rs in Lac EWS": null,
    "Scholarship Annual Rs in Lac Home State": null,
    "Scholarship Annual Rs in Lac Others": null,
    "Cultural Events Yes / No": "Yes",
    "Sports Events Yes / No": "Yes",
    "Technical Events Yes / No": null,
    "Others  Events Yes / No": "Yes"
  },
  {
    "Aishe Code": "C-46517",
    "Name": "Jamia Babul Aloom, Mirgund Budgam",
    "District": "Budgam",
    "Course offered": "B.A,B.SC,B.Com,BBA,IMBA,IMCOM,IHS,IPS",
    "Total Student ENROLLED FY 23 24": 220.1143367035377,
    "Total Student ENROLLED FY 22 23": 303.29194935587645,
    "Passed out FY 23 24": 116.88547773535446,
    "Passed out FY 22 23": null,
    "selected for MS FY 23 24": null,
    "selected for MS FY 22 23": null,
    "No of student placed through Campus FY 23 24": 13.865642894853428,
    "No of student placed through Campus FY 22 23": 5.259981265802117,
    "Average Placement PackageFY 23 24": 1199999.0028373415,
    "Average Placement Package FY 22 23": "4.5 lakh",
    "Hostel facility Yes / No": "yes ",
    "PG Facilities Near college Yes / No": "No",
    "Distance from Railway station": "10.7",
    "No of Seats available General": 421.0701936738789,
    "No of Seats available SC / ST": 43.20577149756851,
    "No of Seats available OBC": 14.109638954698864,
    "No of Seats available Girls": 387.6314232577954,
    "No of Seats available EWS": 3.4349056688571507,
    "No of Seats available Home State": null,
    "No of Seats available Others ": "Management Quota - 15, All India Quota - 9",
    "Facilities offer by College Library Yes / No": "NO",
    "Facilities offer by College Computer Lab Nos": "1",
    "Facilities offer by College Science Lab No": "YES",
    "Facilities offer by College Sports Facility Yes / No": "yes ",
    "Facilities offer by College Medical Facility Yes / No": "yes ",
    "Facilities offer by College Canteen Yes / No": "Yes",
    "Fees Annual Rs in Lac General": 83825.72672017581,
    "Fees Annual Rs in Lac SC / ST": null,
    "Fees Annual Rs in Lac OBC": null,
    "Fees Annual Rs in Lac Girls": null,
    "Fees Annual Rs in Lac EWS": 36000.679899528775,
    "Fees Annual Rs in Lac Home State": null,
    "Fees Annual Rs in Lac Others": "Management Quota - 275000, All India Quota - 250000",
    "Scholarship Annual Rs in Lac General": 25000.65060584587,
    "Scholarship Annual Rs in Lac SC / ST": null,
    "Scholarship Annual Rs in Lac OBC": null,
    "Scholarship Annual Rs in Lac Girls": null,
    "Scholarship Annual Rs in Lac EWS": null,
    "Scholarship Annual Rs in Lac Home State": null,
    "Scholarship Annual Rs in Lac Others": null,
    "Cultural Events Yes / No": "no",
    "Sports Events Yes / No": "Yes",
    "Technical Events Yes / No": null,
    "Others  Events Yes / No": "nss"
  },
  {
    "Aishe Code": "C-46519",
    "Name": "JAMIA-TUL-BANAT, UMER COLONY, LAL BAZAR",
    "District": "Srinagar",
    "Course offered": "B.A Fazila Honours",
    "Total Student ENROLLED FY 23 24": 103.51308118714022,
    "Total Student ENROLLED FY 22 23": 64.42376678479431,
    "Passed out FY 23 24": 114.79457511127067,
    "Passed out FY 22 23": null,
    "selected for MS FY 23 24": null,
    "selected for MS FY 22 23": null,
    "No of student placed through Campus FY 23 24": 14.52295394027667,
    "No of student placed through Campus FY 22 23": 5.533048071064639,
    "Average Placement PackageFY 23 24": 1200000.364606036,
    "Average Placement Package FY 22 23": "4.5 lakh",
    "Hostel facility Yes / No": "Yes",
    "PG Facilities Near college Yes / No": "no",
    "Distance from Railway station": "19.8",
    "No of Seats available General": 200.128184559656,
    "No of Seats available SC / ST": 43.161541113626654,
    "No of Seats available OBC": 12.432361243850304,
    "No of Seats available Girls": 390.0,
    "No of Seats available EWS": 5.051725303648194,
    "No of Seats available Home State": null,
    "No of Seats available Others ": "22",
    "Facilities offer by College Library Yes / No": "Yes",
    "Facilities offer by College Computer Lab Nos": "1",
    "Facilities offer by College Science Lab No": "5",
    "Facilities offer by College Sports Facility Yes / No": "yes",
    "Facilities offer by College Medical Facility Yes / No": "Yes",
    "Facilities offer by College Canteen Yes / No": "Yes",
    "Fees Annual Rs in Lac General": 13250.866939375292,
    "Fees Annual Rs in Lac SC / ST": null,
    "Fees Annual Rs in Lac OBC": null,
    "Fees Annual Rs in Lac Girls": null,
    "Fees Annual Rs in Lac EWS": 35999.50779150256,
    "Fees Annual Rs in Lac Home State": null,
    "Fees Annual Rs in Lac Others": "Management Quota - 275000, All India Quota - 250000",
    "Scholarship Annual Rs in Lac General": 25001.80286139637,
    "Scholarship Annual Rs in Lac SC / ST": null,
    "Scholarship Annual Rs in Lac OBC": null,
    "Scholarship Annual Rs in Lac Girls": null,
    "Scholarship Annual Rs in Lac EWS": null,
    "Scholarship Annual Rs in Lac Home State": null,
    "Scholarship Annual Rs in Lac Others": null,
    "Cultural Events Yes / No": "Yes",
    "Sports Events Yes / No": "Yes",
    "Technical Events Yes / No": null,
    "Others  Events Yes / No": "Yes"
  },
  {
    "Aishe Code": "C-46524",
    "Name": "ISLAMIC ORIENTAL COLLEGE, TRAL",
    "District": "Pulwama",
    "Course offered": "B.A ,B.SC",
    "Total Student ENROLLED FY 23 24": 87.88332424970976,
    "Total Student ENROLLED FY 22 23": 272.3110086603042,
    "Passed out FY 23 24": 114.85162388812452,
    "Passed out FY 22 23": null,
    "selected for MS FY 23 24": null,
    "selected for MS FY 22 23": null,
    "No of student placed through Campus FY 23 24": 14.987832143734025,
    "No of student placed through Campus FY 22 23": 4.478197394161413,
    "Average Placement PackageFY 23 24": 1199998.5169994032,
    "Average Placement Package FY 22 23": "4.5 lakh",
    "Hostel facility Yes / No": "YES",
    "PG Facilities Near college Yes / No": "YES",
    "Distance from Railway station": "1.5",
    "No of Seats available General": 324.3889263130757,
    "No of Seats available SC / ST": 45.66232619248528,
    "No of Seats available OBC": 11.97090645605904,
    "No of Seats available Girls": 389.8409541892624,
    "No of Seats available EWS": 5.716650277388043,
    "No of Seats available Home State": null,
    "No of Seats available Others ": "Management Quota - 15, All India Quota - 9",
    "Facilities offer by College Library Yes / No": "yes ",
    "Facilities offer by College Computer Lab Nos": "YES",
    "Facilities offer by College Science Lab No": "14",
    "Facilities offer by College Sports Facility Yes / No": "Yes",
    "Facilities offer by College Medical Facility Yes / No": "Yes",
    "Facilities offer by College Canteen Yes / No": "yes ",
    "Fees Annual Rs in Lac General": 45747.26184093542,
    "Fees Annual Rs in Lac SC / ST": null,
    "Fees Annual Rs in Lac OBC": null,
    "Fees Annual Rs in Lac Girls": null,
    "Fees Annual Rs in Lac EWS": 36000.0089905989,
    "Fees Annual Rs in Lac Home State": null,
    "Fees Annual Rs in Lac Others": "Management Quota - 275000, All India Quota - 250000",
    "Scholarship Annual Rs in Lac General": 24999.43739338173,
    "Scholarship Annual Rs in Lac SC / ST": null,
    "Scholarship Annual Rs in Lac OBC": null,
    "Scholarship Annual Rs in Lac Girls": null,
    "Scholarship Annual Rs in Lac EWS": null,
    "Scholarship Annual Rs in Lac Home State": null,
    "Scholarship Annual Rs in Lac Others": null,
    "Cultural Events Yes / No": "yes",
    "Sports Events Yes / No": "yes ",
    "Technical Events Yes / No": null,
    "Others  Events Yes / No": "yes"
  },
  {
    "Aishe Code": "C-46539",
    "Name": "KCEF LAW COLLEGE",
    "District": "Pulwama",
    "Course offered": "BA LLB (Integrated 5-year course), LL.B (3 year programme), Bachelors of Education (B.ED)",
    "Total Student ENROLLED FY 23 24": 309.1314203284605,
    "Total Student ENROLLED FY 22 23": 266.0012854380816,
    "Passed out FY 23 24": 115.94146708876332,
    "Passed out FY 22 23": null,
    "selected for MS FY 23 24": null,
    "selected for MS FY 22 23": null,
    "No of student placed through Campus FY 23 24": 15.329280776538528,
    "No of student placed through Campus FY 22 23": 3.8076509423252936,
    "Average Placement PackageFY 23 24": 1200000.1481776652,
    "Average Placement Package FY 22 23": "4.5 lakh",
    "Hostel facility Yes / No": "YES",
    "PG Facilities Near college Yes / No": "NO",
    "Distance from Railway station": "10.7",
    "No of Seats available General": 400.0,
    "No of Seats available SC / ST": 43.99070229577332,
    "No of Seats available OBC": 13.075282600331578,
    "No of Seats available Girls": 390.7587978459816,
    "No of Seats available EWS": 5.002986381836717,
    "No of Seats available Home State": null,
    "No of Seats available Others ": "Management Quota - 15, All India Quota - 9",
    "Facilities offer by College Library Yes / No": "Yes",
    "Facilities offer by College Computer Lab Nos": "1",
    "Facilities offer by College Science Lab No": "YES",
    "Facilities offer by College Sports Facility Yes / No": "yes ",
    "Facilities offer by College Medical Facility Yes / No": "yes ",
    "Facilities offer by College Canteen Yes / No": "yes ",
    "Fees Annual Rs in Lac General": 181148.90291818004,
    "Fees Annual Rs in Lac SC / ST": null,
    "Fees Annual Rs in Lac OBC": null,
    "Fees Annual Rs in Lac Girls": null,
    "Fees Annual Rs in Lac EWS": 36000.02104104533,
    "Fees Annual Rs in Lac Home State": null,
    "Fees Annual Rs in Lac Others": "Management Quota - 275000, All India Quota - 250000",
    "Scholarship Annual Rs in Lac General": 25000.22029254614,
    "Scholarship Annual Rs in Lac SC / ST": null,
    "Scholarship Annual Rs in Lac OBC": null,
    "Scholarship Annual Rs in Lac Girls": null,
    "Scholarship Annual Rs in Lac EWS": null,
    "Scholarship Annual Rs in Lac Home State": null,
    "Scholarship Annual Rs in Lac Others": null,
    "Cultural Events Yes / No": "Yes",
    "Sports Events Yes / No": "Yes ",
    "Technical Events Yes / No": null,
    "Others  Events Yes / No": "Yes"
  },
  {
    "Aishe Code": "C-46540",
    "Name": "SOPORE LAW COLLEGE",
    "District": "Baramulla",
    "Course offered": "BA LLB, LLB",
    "Total Student ENROLLED FY 23 24": 82.0,
    "Total Student ENROLLED FY 22 23": 145.0,
    "Passed out FY 23 24": 113.77615239690748,
    "Passed out FY 22 23": null,
    "selected for MS FY 23 24": null,
    "selected for MS FY 22 23": null,
    "No of student placed through Campus FY 23 24": 13.557055421622788,
    "No of student placed through Campus FY 22 23": 2.585119421523016,
    "Average Placement PackageFY 23 24": 1199999.191227605,
    "Average Placement Package FY 22 23": "4.5 lakh",
    "Hostel facility Yes / No": "no",
    "PG Facilities Near college Yes / No": "No",
    "Distance from Railway station": "2",
    "No of Seats available General": 224.78193065851335,
    "No of Seats available SC / ST": 44.35695651671106,
    "No of Seats available OBC": 13.022642286751928,
    "No of Seats available Girls": 391.2706764281166,
    "No of Seats available EWS": 4.677771262010683,
    "No of Seats available Home State": null,
    "No of Seats available Others ": "22",
    "Facilities offer by College Library Yes / No": "yes ",
    "Facilities offer by College Computer Lab Nos": "YES",
    "Facilities offer by College Science Lab No": "14",
    "Facilities offer by College Sports Facility Yes / No": "Yes",
    "Facilities offer by College Medical Facility Yes / No": "yes ",
    "Facilities offer by College Canteen Yes / No": "yes",
    "Fees Annual Rs in Lac General": 61662.234019136624,
    "Fees Annual Rs in Lac SC / ST": null,
    "Fees Annual Rs in Lac OBC": null,
    "Fees Annual Rs in Lac Girls": null,
    "Fees Annual Rs in Lac EWS": 35997.89526085263,
    "Fees Annual Rs in Lac Home State": null,
    "Fees Annual Rs in Lac Others": "Management Quota - 275000, All India Quota - 250000",
    "Scholarship Annual Rs in Lac General": 24998.09926823228,
    "Scholarship Annual Rs in Lac SC / ST": null,
    "Scholarship Annual Rs in Lac OBC": null,
    "Scholarship Annual Rs in Lac Girls": null,
    "Scholarship Annual Rs in Lac EWS": null,
    "Scholarship Annual Rs in Lac Home State": null,
    "Scholarship Annual Rs in Lac Others": null,
    "Cultural Events Yes / No": "Yes",
    "Sports Events Yes / No": "yes ",
    "Technical Events Yes / No": null,
    "Others  Events Yes / No": "Yes"
  },
  {
    "Aishe Code": "C-46535",
    "Name": "MEX WELL COLLEGE OF EDUCATION",
    "District": "Pulwama",
    "Course offered": "Bachelor of Education (B.Ed.)\r\n",
    "Total Student ENROLLED FY 23 24": 223.3094726151957,
    "Total Student ENROLLED FY 22 23": 108.6010199406803,
    "Passed out FY 23 24": 114.91619660391068,
    "Passed out FY 22 23": null,
    "selected for MS FY 23 24": null,
    "selected for MS FY 22 23": null,
    "No of student placed through Campus FY 23 24": 12.229745763688191,
    "No of student placed through Campus FY 22 23": 5.083221074766467,
    "Average Placement PackageFY 23 24": 1199999.3080582337,
    "Average Placement Package FY 22 23": "4.5 lakh",
    "Hostel facility Yes / No": "Yes",
    "PG Facilities Near college Yes / No": "No",
    "Distance from Railway station": "10.8",
    "No of Seats available General": 180.0,
    "No of Seats available SC / ST": 45.18013588099949,
    "No of Seats available OBC": 12.65502651931164,
    "No of Seats available Girls": 389.6229023257955,
    "No of Seats available EWS": 3.7730209209358274,
    "No of Seats available Home State": null,
    "No of Seats available Others ": "Management Quota - 15, All India Quota - 9",
    "Facilities offer by College Library Yes / No": "Yes",
    "Facilities offer by College Computer Lab Nos": "1",
    "Facilities offer by College Science Lab No": "YES",
    "Facilities offer by College Sports Facility Yes / No": "Yes",
    "Facilities offer by College Medical Facility Yes / No": "Yes",
    "Facilities offer by College Canteen Yes / No": "Yes",
    "Fees Annual Rs in Lac General": 94611.6716346381,
    "Fees Annual Rs in Lac SC / ST": null,
    "Fees Annual Rs in Lac OBC": null,
    "Fees Annual Rs in Lac Girls": null,
    "Fees Annual Rs in Lac EWS": 36000.36322834779,
    "Fees Annual Rs in Lac Home State": null,
    "Fees Annual Rs in Lac Others": "Management Quota - 275000, All India Quota - 250000",
    "Scholarship Annual Rs in Lac General": 25000.06047785829,
    "Scholarship Annual Rs in Lac SC / ST": null,
    "Scholarship Annual Rs in Lac OBC": null,
    "Scholarship Annual Rs in Lac Girls": null,
    "Scholarship Annual Rs in Lac EWS": null,
    "Scholarship Annual Rs in Lac Home State": null,
    "Scholarship Annual Rs in Lac Others": null,
    "Cultural Events Yes / No": "yes ",
    "Sports Events Yes / No": "yes",
    "Technical Events Yes / No": null,
    "Others  Events Yes / No": "nss"
  },
  {
    "Aishe Code": "C-47452",
    "Name": "COMPOSITE REGIONAL CENTRE, MINISTRY OF SOCIAL JUSTICE EMPOWERMENT, BEMINA",
    "District": "Srinagar",
    "Course offered": "Bachelors in Physiotherapy (BPT), B.Ed Special Education (ID), P.G Diploma in Rehabilitation Psychology (PGDRP), P.G. Diploma in Early Intervention",
    "Total Student ENROLLED FY 23 24": 174.3993979380544,
    "Total Student ENROLLED FY 22 23": 277.5463742185175,
    "Passed out FY 23 24": 115.36994332385748,
    "Passed out FY 22 23": null,
    "selected for MS FY 23 24": null,
    "selected for MS FY 22 23": null,
    "No of student placed through Campus FY 23 24": 15.170302455433882,
    "No of student placed through Campus FY 22 23": 5.199687805502043,
    "Average Placement PackageFY 23 24": 1200000.9376839136,
    "Average Placement Package FY 22 23": "4.5 lakh",
    "Hostel facility Yes / No": "Yes",
    "PG Facilities Near college Yes / No": "YES",
    "Distance from Railway station": "8.9",
    "No of Seats available General": 87.0,
    "No of Seats available SC / ST": 44.65916685840252,
    "No of Seats available OBC": 12.069512562661542,
    "No of Seats available Girls": 391.56724809845,
    "No of Seats available EWS": 4.026056700760885,
    "No of Seats available Home State": null,
    "No of Seats available Others ": "22",
    "Facilities offer by College Library Yes / No": "yes ",
    "Facilities offer by College Computer Lab Nos": "YES",
    "Facilities offer by College Science Lab No": "YES",
    "Facilities offer by College Sports Facility Yes / No": "yes",
    "Facilities offer by College Medical Facility Yes / No": "yes ",
    "Facilities offer by College Canteen Yes / No": "Yes",
    "Fees Annual Rs in Lac General": -25754.15513215233,
    "Fees Annual Rs in Lac SC / ST": null,
    "Fees Annual Rs in Lac OBC": null,
    "Fees Annual Rs in Lac Girls": null,
    "Fees Annual Rs in Lac EWS": 36000.55718108224,
    "Fees Annual Rs in Lac Home State": null,
    "Fees Annual Rs in Lac Others": "Management Quota - 275000, All India Quota - 250000",
    "Scholarship Annual Rs in Lac General": 25000.50154781473,
    "Scholarship Annual Rs in Lac SC / ST": null,
    "Scholarship Annual Rs in Lac OBC": null,
    "Scholarship Annual Rs in Lac Girls": null,
    "Scholarship Annual Rs in Lac EWS": null,
    "Scholarship Annual Rs in Lac Home State": null,
    "Scholarship Annual Rs in Lac Others": null,
    "Cultural Events Yes / No": "Yes",
    "Sports Events Yes / No": "Yes",
    "Technical Events Yes / No": null,
    "Others  Events Yes / No": "Yes"
  },
  {
    "Aishe Code": "C-47441",
    "Name": "MODEL GOVERNMENT DEGREE COLLEGE, CHRARI SHARIEF, ",
    "District": "Budgam",
    "Course offered": "Bachelor of Science, Bachelor of Commerce\r\n, Bachelor of Computer Applications, Bachelor of Arts",
    "Total Student ENROLLED FY 23 24": 238.0,
    "Total Student ENROLLED FY 22 23": 167.79217852673673,
    "Passed out FY 23 24": 115.0,
    "Passed out FY 22 23": null,
    "selected for MS FY 23 24": null,
    "selected for MS FY 22 23": null,
    "No of student placed through Campus FY 23 24": 14.199604105203145,
    "No of student placed through Campus FY 22 23": 7.66432306459571,
    "Average Placement PackageFY 23 24": 1200000.0640491566,
    "Average Placement Package FY 22 23": "4.5 lakh",
    "Hostel facility Yes / No": "yes",
    "PG Facilities Near college Yes / No": "yes",
    "Distance from Railway station": "23",
    "No of Seats available General": 23.32830057698598,
    "No of Seats available SC / ST": 44.42947407353196,
    "No of Seats available OBC": 11.952688128209068,
    "No of Seats available Girls": 388.0972738517837,
    "No of Seats available EWS": 5.212649984824432,
    "No of Seats available Home State": null,
    "No of Seats available Others ": "Management Quota - 15, All India Quota - 9",
    "Facilities offer by College Library Yes / No": "Yes",
    "Facilities offer by College Computer Lab Nos": "2",
    "Facilities offer by College Science Lab No": "4",
    "Facilities offer by College Sports Facility Yes / No": "Yes",
    "Facilities offer by College Medical Facility Yes / No": "YES",
    "Facilities offer by College Canteen Yes / No": "Yes",
    "Fees Annual Rs in Lac General": 33429.37799483966,
    "Fees Annual Rs in Lac SC / ST": null,
    "Fees Annual Rs in Lac OBC": null,
    "Fees Annual Rs in Lac Girls": null,
    "Fees Annual Rs in Lac EWS": 35999.248421502234,
    "Fees Annual Rs in Lac Home State": null,
    "Fees Annual Rs in Lac Others": "Management Quota - 275000, All India Quota - 250000",
    "Scholarship Annual Rs in Lac General": 24999.196734376244,
    "Scholarship Annual Rs in Lac SC / ST": null,
    "Scholarship Annual Rs in Lac OBC": null,
    "Scholarship Annual Rs in Lac Girls": null,
    "Scholarship Annual Rs in Lac EWS": null,
    "Scholarship Annual Rs in Lac Home State": null,
    "Scholarship Annual Rs in Lac Others": null,
    "Cultural Events Yes / No": "Yes",
    "Sports Events Yes / No": "Yes",
    "Technical Events Yes / No": null,
    "Others  Events Yes / No": "Yes"
  },
  {
    "Aishe Code": "C-48473",
    "Name": "GOVERNMENT DEGREE COLLEGE, SURANKOT",
    "District": "Poonch",
    "Course offered": "Bachelor of Arts, Bachelor of Science",
    "Total Student ENROLLED FY 23 24": 194.28090778556844,
    "Total Student ENROLLED FY 22 23": 193.00252626232168,
    "Passed out FY 23 24": 116.47362109395898,
    "Passed out FY 22 23": null,
    "selected for MS FY 23 24": null,
    "selected for MS FY 22 23": null,
    "No of student placed through Campus FY 23 24": 14.27655954698082,
    "No of student placed through Campus FY 22 23": 2.887849029014339,
    "Average Placement PackageFY 23 24": 1200000.9173455895,
    "Average Placement Package FY 22 23": "4.5 lakh",
    "Hostel facility Yes / No": "YES",
    "PG Facilities Near college Yes / No": "No",
    "Distance from Railway station": "155",
    "No of Seats available General": 80.0,
    "No of Seats available SC / ST": 45.0,
    "No of Seats available OBC": 13.0,
    "No of Seats available Girls": 389.8986710369085,
    "No of Seats available EWS": 5.621822863596647,
    "No of Seats available Home State": null,
    "No of Seats available Others ": "22",
    "Facilities offer by College Library Yes / No": "Yes",
    "Facilities offer by College Computer Lab Nos": "1",
    "Facilities offer by College Science Lab No": "14",
    "Facilities offer by College Sports Facility Yes / No": "Yes",
    "Facilities offer by College Medical Facility Yes / No": "yes",
    "Facilities offer by College Canteen Yes / No": "YES",
    "Fees Annual Rs in Lac General": 120795.4566289258,
    "Fees Annual Rs in Lac SC / ST": null,
    "Fees Annual Rs in Lac OBC": null,
    "Fees Annual Rs in Lac Girls": null,
    "Fees Annual Rs in Lac EWS": 35999.01733487968,
    "Fees Annual Rs in Lac Home State": null,
    "Fees Annual Rs in Lac Others": "Management Quota - 275000, All India Quota - 250000",
    "Scholarship Annual Rs in Lac General": 24999.41819196084,
    "Scholarship Annual Rs in Lac SC / ST": null,
    "Scholarship Annual Rs in Lac OBC": null,
    "Scholarship Annual Rs in Lac Girls": null,
    "Scholarship Annual Rs in Lac EWS": null,
    "Scholarship Annual Rs in Lac Home State": null,
    "Scholarship Annual Rs in Lac Others": null,
    "Cultural Events Yes / No": "Yes",
    "Sports Events Yes / No": "Yes",
    "Technical Events Yes / No": null,
    "Others  Events Yes / No": "Yes"
  },
  {
    "Aishe Code": "C-48525",
    "Name": "Government Degree College,Magam",
    "District": "Budgam",
    "Course offered": "B.Ed",
    "Total Student ENROLLED FY 23 24": 161.78339358334037,
    "Total Student ENROLLED FY 22 23": 331.4849968708602,
    "Passed out FY 23 24": 116.14608063065968,
    "Passed out FY 22 23": null,
    "selected for MS FY 23 24": null,
    "selected for MS FY 22 23": null,
    "No of student placed through Campus FY 23 24": 13.606355607505202,
    "No of student placed through Campus FY 22 23": 3.2465930710507207,
    "Average Placement PackageFY 23 24": 1199999.8663820336,
    "Average Placement Package FY 22 23": "4.5 lakh",
    "Hostel facility Yes / No": "No",
    "PG Facilities Near college Yes / No": "NO",
    "Distance from Railway station": " 0.5 km",
    "No of Seats available General": 119.21232746893878,
    "No of Seats available SC / ST": 45.42380345745279,
    "No of Seats available OBC": 12.496342074494056,
    "No of Seats available Girls": 388.6360279751634,
    "No of Seats available EWS": 5.853081579162152,
    "No of Seats available Home State": null,
    "No of Seats available Others ": "22",
    "Facilities offer by College Library Yes / No": "YES",
    "Facilities offer by College Computer Lab Nos": "1",
    "Facilities offer by College Science Lab No": "YES",
    "Facilities offer by College Sports Facility Yes / No": "yes ",
    "Facilities offer by College Medical Facility Yes / No": "Yes",
    "Facilities offer by College Canteen Yes / No": "yes",
    "Fees Annual Rs in Lac General": 79557.91990175398,
    "Fees Annual Rs in Lac SC / ST": null,
    "Fees Annual Rs in Lac OBC": null,
    "Fees Annual Rs in Lac Girls": null,
    "Fees Annual Rs in Lac EWS": 36000.06451764168,
    "Fees Annual Rs in Lac Home State": null,
    "Fees Annual Rs in Lac Others": "Management Quota - 275000, All India Quota - 250000",
    "Scholarship Annual Rs in Lac General": 24998.927338912097,
    "Scholarship Annual Rs in Lac SC / ST": null,
    "Scholarship Annual Rs in Lac OBC": null,
    "Scholarship Annual Rs in Lac Girls": null,
    "Scholarship Annual Rs in Lac EWS": null,
    "Scholarship Annual Rs in Lac Home State": null,
    "Scholarship Annual Rs in Lac Others": null,
    "Cultural Events Yes / No": "Yes",
    "Sports Events Yes / No": "yes",
    "Technical Events Yes / No": null,
    "Others  Events Yes / No": "nss"
  },
  {
    "Aishe Code": "C-48526",
    "Name": "GOVERNMENT DEGREE COLLEGE, TANGMARG",
    "District": "Baramulla",
    "Course offered": "B.Sc in Physics Computer App. Maths, B.Sc in Physics Chemistry Maths, B.A in App Maths, Comp App, Hindi, B.A in Maths, B.A in App Maths, Comp App, Economicss B.A in Education Philosophy Sociology, B.A in Pol. Science History Sociology",
    "Total Student ENROLLED FY 23 24": 171.0,
    "Total Student ENROLLED FY 22 23": 322.0,
    "Passed out FY 23 24": 114.76002591227255,
    "Passed out FY 22 23": null,
    "selected for MS FY 23 24": null,
    "selected for MS FY 22 23": null,
    "No of student placed through Campus FY 23 24": 13.655277241808133,
    "No of student placed through Campus FY 22 23": 5.228698710897543,
    "Average Placement PackageFY 23 24": 1200000.3559627696,
    "Average Placement Package FY 22 23": "4.5 lakh",
    "Hostel facility Yes / No": "yes",
    "PG Facilities Near college Yes / No": "no",
    "Distance from Railway station": "20.8",
    "No of Seats available General": 142.04090642414334,
    "No of Seats available SC / ST": 44.55365898761849,
    "No of Seats available OBC": 13.601870298268238,
    "No of Seats available Girls": 389.5510309978173,
    "No of Seats available EWS": 3.357081741357403,
    "No of Seats available Home State": null,
    "No of Seats available Others ": "22",
    "Facilities offer by College Library Yes / No": "yes",
    "Facilities offer by College Computer Lab Nos": "1",
    "Facilities offer by College Science Lab No": "14",
    "Facilities offer by College Sports Facility Yes / No": "Yes",
    "Facilities offer by College Medical Facility Yes / No": "YES",
    "Facilities offer by College Canteen Yes / No": "Yes",
    "Fees Annual Rs in Lac General": 11946.964209141894,
    "Fees Annual Rs in Lac SC / ST": null,
    "Fees Annual Rs in Lac OBC": null,
    "Fees Annual Rs in Lac Girls": null,
    "Fees Annual Rs in Lac EWS": 35999.12031447472,
    "Fees Annual Rs in Lac Home State": null,
    "Fees Annual Rs in Lac Others": "Management Quota - 275000, All India Quota - 250000",
    "Scholarship Annual Rs in Lac General": 25000.55305074823,
    "Scholarship Annual Rs in Lac SC / ST": null,
    "Scholarship Annual Rs in Lac OBC": null,
    "Scholarship Annual Rs in Lac Girls": null,
    "Scholarship Annual Rs in Lac EWS": null,
    "Scholarship Annual Rs in Lac Home State": null,
    "Scholarship Annual Rs in Lac Others": null,
    "Cultural Events Yes / No": "no",
    "Sports Events Yes / No": "yes ",
    "Technical Events Yes / No": null,
    "Others  Events Yes / No": "yes"
  },
  {
    "Aishe Code": "C-48527",
    "Name": "GOVERNMENT DEGREE COLLEGE, KANGAN",
    "District": "Ganderbal",
    "Course offered": "Bachelor of Commerce General CBCS, Bachelor of Science, Bachelor of Art (CBCS), Bsc With Botany",
    "Total Student ENROLLED FY 23 24": 272.73064740006095,
    "Total Student ENROLLED FY 22 23": 413.9548005455819,
    "Passed out FY 23 24": 115.15031595222676,
    "Passed out FY 22 23": null,
    "selected for MS FY 23 24": null,
    "selected for MS FY 22 23": null,
    "No of student placed through Campus FY 23 24": 14.633909726366491,
    "No of student placed through Campus FY 22 23": 3.643995846623748,
    "Average Placement PackageFY 23 24": 1200000.819295198,
    "Average Placement Package FY 22 23": "4.5 lakh",
    "Hostel facility Yes / No": "yes ",
    "PG Facilities Near college Yes / No": "No",
    "Distance from Railway station": "48",
    "No of Seats available General": 40.0,
    "No of Seats available SC / ST": 45.88309997729138,
    "No of Seats available OBC": 12.45499048409392,
    "No of Seats available Girls": 391.2888848340549,
    "No of Seats available EWS": 7.120315848297253,
    "No of Seats available Home State": null,
    "No of Seats available Others ": "Management Quota - 15, All India Quota - 9",
    "Facilities offer by College Library Yes / No": "Yes",
    "Facilities offer by College Computer Lab Nos": "2",
    "Facilities offer by College Science Lab No": "1",
    "Facilities offer by College Sports Facility Yes / No": "Yes",
    "Facilities offer by College Medical Facility Yes / No": "NO",
    "Facilities offer by College Canteen Yes / No": "YES",
    "Fees Annual Rs in Lac General": -26637.466344682893,
    "Fees Annual Rs in Lac SC / ST": null,
    "Fees Annual Rs in Lac OBC": null,
    "Fees Annual Rs in Lac Girls": null,
    "Fees Annual Rs in Lac EWS": 36000.33301039339,
    "Fees Annual Rs in Lac Home State": null,
    "Fees Annual Rs in Lac Others": "Management Quota - 275000, All India Quota - 250000",
    "Scholarship Annual Rs in Lac General": 25000.80502457278,
    "Scholarship Annual Rs in Lac SC / ST": null,
    "Scholarship Annual Rs in Lac OBC": null,
    "Scholarship Annual Rs in Lac Girls": null,
    "Scholarship Annual Rs in Lac EWS": null,
    "Scholarship Annual Rs in Lac Home State": null,
    "Scholarship Annual Rs in Lac Others": null,
    "Cultural Events Yes / No": "Yes",
    "Sports Events Yes / No": "Yes ",
    "Technical Events Yes / No": null,
    "Others  Events Yes / No": "Yes"
  }
]